{
  "insp_id": "231151056060647",
  "layout": "a",
  "customer_id": "3037",
  "customer_name": "Bill E Delozier",
  "customer_addr": "2855 Parkway\nPigeon Forge, TN 37868",
  "certificate": "63-C-0103",
  "site_id": "001",
  "site_name": "BILL DELOZIER",
  "insp_type": "ROUTINE INSPECTION",
  "date": "18-AUG-2015",
  "report_date": "18-AUG-2015",
  "citations": [
    {
      "code": "2.40(b)(2)",
      "kind": "Direct",
      "repeat": false,
      "desc": "ATTENDING VETERINARIAN AND ADEQUATE VETERINARY CARE (DEALERS AND EXHIBITORS).",
      "narrative": "There is an older female bear named (cid:28)Honey\" that has a large area of thinning hair thru out her lower back. In\naddition her eyes appear glazed and she has difficulty with her range of movement. Due to the lack of an attending\nveterinarian(cid:25)s evaluation it is difficult for the facility representative to determine what treatment should be for the\nolder female bear. Facility has noted the issues and should contact the attending veterinarian for evaluation of older\nfemale bear. Correct by August 25, 2015\nAn exit briefing was conducted with facility representative."
    }
  ],
  "narrative": "2.40(b)(2)           DIRECT\nATTENDING VETERINARIAN AND ADEQUATE VETERINARY CARE (DEALERS AND EXHIBITORS).\nThere is an older female bear named (cid:28)Honey\" that has a large area of thinning hair thru out her lower back. In\naddition her eyes appear glazed and she has difficulty with her range of movement. Due to the lack of an attending\nveterinarian(cid:25)s evaluation it is difficult for the facility representative to determine what treatment should be for the\nolder female bear. Facility has noted the issues and should contact the attending veterinarian for evaluation of older\nfemale bear. Correct by August 25, 2015\nAn exit briefing was conducted with facility representative.",
  "animals_total": 5,
  "species": [
    {
      "count": 5,
      "scientific": "Ursus thibetanus",
      "common": "ASIATIC BLACK BEAR"
    }
  ]
}