{
  "insp_id": "2016082569586525",
  "layout": "a",
  "customer_id": "826",
  "customer_name": "University Of North Carolina",
  "customer_addr": "312 South Building Cb#4000\nChapel Hill, NC 27599",
  "certificate": "55-R-0004",
  "site_id": "001",
  "site_name": "DIVISION OF LABORATORY ANIMAL MEDICINE",
  "insp_type": "FOCUSED INSPECTION",
  "date": "28-AUG-2019",
  "report_date": "28-AUG-2019",
  "citations": [],
  "narrative": "No non-compliant items identified during this inspection.\nThis inspection and exit interview were conducted with facility representatives.",
  "animals_total": 2,
  "species": [
    {
      "count": 2,
      "scientific": "Meriones unguiculatus",
      "common": "MONGOLIAN GERBIL (COMMON PET / RESEARCH VARIETY)"
    }
  ]
}