{
  "insp_id": "238141145590926",
  "layout": "a",
  "customer_id": "323143",
  "customer_name": "Leroy Detweiler",
  "customer_addr": "28138 Jaguar Pl\nPrinceton, MO 64673",
  "certificate": "43-A-5786",
  "site_id": "001",
  "site_name": "LEROY DETWEILER",
  "insp_type": "ROUTINE INSPECTION",
  "date": "26-AUG-2014",
  "report_date": "26-AUG-2014",
  "citations": [],
  "narrative": "No non-compliant items identified during this inspection. \n \nInspection and exit interview conducted with facility representative.",
  "animals_total": 78,
  "species": [
    {
      "count": 61,
      "scientific": "Canis lupus familiaris",
      "common": "DOG ADULT"
    },
    {
      "count": 17,
      "scientific": "Canis lupus familiaris",
      "common": "DOG PUPPY"
    }
  ]
}