{
  "insp_id": "INS-0001295494",
  "layout": "c",
  "customer_id": "325095",
  "customer_name": "Robert J Mills",
  "customer_addr": "4091 Matanzas Drive\nMyrtle Beach, SC 29577",
  "certificate": "56-B-0128",
  "site_id": "001",
  "site_name": "ROBERT MILLS",
  "insp_type": "ROUTINE INSPECTION",
  "date": "23-APR-2025",
  "report_date": "24-APR-2025",
  "citations": [],
  "narrative": "No non-compliant items identified during this inspection. \n \nThis inspection and exit interview were conducted with the facility representatives. \n \n n",
  "animals_total": 217,
  "species": [
    {
      "count": 5,
      "scientific": "Cavia porcellus",
      "common": "DOMESTIC GUINEA PIG"
    },
    {
      "count": 117,
      "scientific": "Petaurus breviceps",
      "common": "SUGAR GLIDER"
    },
    {
      "count": 17,
      "scientific": "Atelerix albiventris",
      "common": "FOUR-TOED HEDGEHOG (MOST COMMON PET HEDGEHOG)"
    },
    {
      "count": 6,
      "scientific": "Phodopus roborovskii",
      "common": "ROBOROVSKI'S DWARF HAMSTER"
    },
    {
      "count": 5,
      "scientific": "Mesocricetus auratus",
      "common": "SYRIAN / GOLDEN HAMSTER"
    },
    {
      "count": 12,
      "scientific": "Oryctolagus cuniculus",
      "common": "DOMESTIC RABBIT / EUROPEAN RABBIT"
    },
    {
      "count": 12,
      "scientific": "Chinchilla lanigera",
      "common": "CHINCHILLA"
    },
    {
      "count": 10,
      "scientific": "Melopsittacus undulatus",
      "common": "BUDGERIGAR / BUDGIE / COMMON PARAKEET / SHELL"
    },
    {
      "count": 6,
      "scientific": "Nymphicus hollandicus",
      "common": "COCKATIEL"
    },
    {
      "count": 1,
      "scientific": "Amazona auropalliata",
      "common": "YELLOW-NAPED PARROT / YELLOW-NAPED AMAZON"
    },
    {
      "count": 7,
      "scientific": "Pyrrhura molinae",
      "common": "GREEN-CHEEKED PARAKEET / GREEN-CHEEKED CONURE"
    },
    {
      "count": 1,
      "scientific": "Ara ararauna",
      "common": "BLUE-AND-YELLOW MACAW / BLUE-AND-GOLD MACAW"
    },
    {
      "count": 1,
      "scientific": "Agapornis roseicollis",
      "common": "ROSY-FACED LOVEBIRD"
    },
    {
      "count": 1,
      "scientific": "Psittacula krameri",
      "common": "ROSE-RINGED PARAKEET"
    },
    {
      "count": 3,
      "scientific": "Mustela putorius furo",
      "common": "DOMESTIC FERRET"
    },
    {
      "count": 1,
      "scientific": "Psittacus erithacus",
      "common": "CONGO AFRICAN GREY PARROT / GRAY PARROT"
    },
    {
      "count": 2,
      "scientific": "Lonchura punctulata",
      "common": "SCALY-BREASTED MUNIA / NUTMEG MANNIKIN"
    },
    {
      "count": 2,
      "scientific": "Ploceus aurantius",
      "common": "ORANGE WEAVER"
    },
    {
      "count": 6,
      "scientific": "Lonchura striata domestica",
      "common": "SOCIETY FINCH / BENGALESE FINCH"
    },
    {
      "count": 2,
      "scientific": "Graphiurus lorraineus",
      "common": "AFRICAN DORMOUSE"
    }
  ]
}