{
  "insp_id": "2016082568033946",
  "layout": "a",
  "customer_id": "5987",
  "customer_name": "Charles L Brown",
  "customer_addr": "Doris Brown\n2909 Roasting Ear Rd\nOnia, AR 72663",
  "certificate": "71-A-0611",
  "site_id": "001",
  "site_name": "CHARLES & DORIS BROWN",
  "insp_type": "ROUTINE INSPECTION",
  "date": "08-DEC-2016",
  "animals_total": 31,
  "species": [
    {
      "count": 21,
      "scientific": "Canis lupus familiaris",
      "common": "DOG ADULT"
    },
    {
      "count": 10,
      "scientific": "Canis lupus familiaris",
      "common": "DOG PUPPY"
    }
  ]
}