{
  "insp_id": "INS-0000804562",
  "layout": "c",
  "customer_id": "328622",
  "customer_name": "UNIVERSITY OF WEST FLORIDA",
  "customer_addr": "11000 UNIVERSITY PARKWAY BLDG 11/113\nPENSACOLA, FL 32514",
  "certificate": "58-R-0156",
  "site_id": "001",
  "site_name": "UNIVERSITY OF WEST FLORIDA",
  "insp_type": "ROUTINE INSPECTION",
  "date": "13-JUL-2022",
  "report_date": "13-JUL-2022",
  "citations": [],
  "narrative": "No non-compliant items identified during this inspection. \n \nThis inspection and exit interview were conducted with the facility representative. \n \n n",
  "animals_total": 0,
  "species": [
    {
      "count": 0,
      "scientific": "NONE",
      "common": "NONE"
    }
  ]
}