{
  "insp_id": "2016082568297937",
  "layout": "a",
  "customer_id": "501584",
  "customer_name": "Travis Hoehne",
  "customer_addr": "380 Algonquin Lane\nJackson, MO 63755",
  "certificate": "43-A-6207",
  "site_id": "001",
  "site_name": "TRAVIS HOEHNE",
  "insp_type": "PRELICENSE INSPECTION #1",
  "date": "24-MAY-2017",
  "report_date": "24-MAY-2017",
  "citations": [],
  "narrative": "This pre-license inspection #1 and exit interview was conducted with the owner by Curt McGruder-ACI.\nNo noncompliances identified this inspection.\nFacility is to be licensed as a class \"A\" dealer.\nFacility will submit the license fee to the regional office.\nReviewed the maintaining of the USDA license.\nNo covered activities may occur before receipt of the USDA license.",
  "animals_total": 12,
  "species": [
    {
      "count": 12,
      "scientific": "Oryctolagus cuniculus",
      "common": "DOMESTIC RABBIT / EUROPEAN RABBIT"
    }
  ]
}