{
  "insp_id": "2016090000607393",
  "layout": "a",
  "customer_id": "321345",
  "customer_name": "PETER SCHWARTZ",
  "customer_addr": "75 MOUNTAIN ROAD\nSEYMOUR, MO 65746",
  "certificate": "43-A-5544",
  "site_id": "001",
  "site_name": "PETER T. SCHWARTZ",
  "insp_type": "ROUTINE INSPECTION",
  "date": "12-MAY-2021",
  "report_date": "12-MAY-2021",
  "animals_total": 97,
  "species": [
    {
      "count": 55,
      "scientific": "Canis lupus familiaris",
      "common": "DOG ADULT"
    },
    {
      "count": 42,
      "scientific": "Canis lupus familiaris",
      "common": "DOG PUPPY"
    }
  ]
}