{
  "insp_id": "2016082569215854",
  "layout": "a",
  "customer_id": "4767",
  "customer_name": "Audubon Nature Institute",
  "customer_addr": "P O Box 4327\nNew Orleans, LA 70178",
  "certificate": "72-C-0141",
  "site_id": "001",
  "site_name": "AUDUBON NATURE INSTITUTE",
  "insp_type": "ROUTINE INSPECTION",
  "date": "16-JUL-2018",
  "report_date": "17-JUL-2018",
  "animals_total": 9,
  "species": [
    {
      "count": 5,
      "scientific": "Lama pacos",
      "common": "ALPACA"
    },
    {
      "count": 1,
      "scientific": "Panthera onca",
      "common": "JAGUAR"
    },
    {
      "count": 3,
      "scientific": "Vulpes vulpes",
      "common": "RED FOX (INCLUDES SILVER FOX & CROSS FOX)"
    }
  ]
}