{
  "insp_id": "2016090000763782",
  "layout": "b",
  "customer_id": "7854",
  "customer_name": "Antibodies Inc.",
  "customer_addr": "P. O. Box 1560\nDavis, CA 95617",
  "certificate": "93-B-0222",
  "site_id": "001",
  "site_name": "ANTIBODIES, INC.",
  "insp_type": "ROUTINE INSPECTION",
  "date": "03-FEB-2022",
  "report_date": "08-FEB-2022",
  "citations": [
    {
      "code": "3.125(a)",
      "kind": "",
      "repeat": false,
      "desc": "Facilities, general.",
      "narrative": "In several areas of the goat and alpaca pens, the fence had areas of damage and loose wires with sharp points that could\npotentially injure the covered animals in the enclosures. Outdoor housing facilities shall be structurally sound and\nmaintained in good repair to protect the animals from injury.\nCorrect by 15 March 2022\nThis inspection and exit interview were conducted with the IACUC chair.\nEnd Section"
    }
  ],
  "narrative": "3.125(a) \n   \nFacilities, general. \nIn several areas of the goat and alpaca pens, the fence had areas of damage and loose wires with sharp points that could \npotentially injure the covered animals in the enclosures. Outdoor housing facilities shall be structurally sound and \nmaintained in good repair to protect the animals from injury. \n \nCorrect by 15 March 2022 \n \nThis inspection and exit interview were conducted with the IACUC chair. \n \nEnd Section",
  "animals_total": 61,
  "species": [
    {
      "count": 8,
      "scientific": "Lama pacos",
      "common": "ALPACA"
    },
    {
      "count": 45,
      "scientific": "Oryctolagus cuniculus",
      "common": "DOMESTIC RABBIT / EUROPEAN RABBIT"
    },
    {
      "count": 8,
      "scientific": "Capra hircus",
      "common": "DOMESTIC GOAT"
    }
  ]
}