{
  "insp_id": "2016082568280521",
  "layout": "a",
  "customer_id": "15304",
  "customer_name": "Bobbi Colorado",
  "customer_addr": "8929 Hwy 290 West\nAustin, TX 78736",
  "certificate": "74-C-0633",
  "site_id": "001",
  "site_name": "Bobbi Colorado",
  "insp_type": "ROUTINE INSPECTION",
  "date": "08-MAY-2017",
  "report_date": "10-MAY-2017",
  "animals_total": 3,
  "species": [
    {
      "count": 1,
      "scientific": "Canis lupus familiaris",
      "common": "DOG ADULT"
    },
    {
      "count": 2,
      "scientific": "Nomascus leucogenys",
      "common": "WHITE-CHEEKED GIBBON"
    }
  ]
}