{
  "insp_id": "240151628080866",
  "layout": "a",
  "customer_id": "327384",
  "customer_name": "Nicholas Smith",
  "customer_addr": "Rebecca Olate\nRichard Olate\n33432 County Road 437\nSorrento, FL 32776",
  "certificate": "58-C-1036",
  "site_id": "TRA",
  "site_name": "NICHOLAS SMITH & REBECCA OLATE & RICHARD OLATE",
  "insp_type": "ROUTINE INSPECTION",
  "date": "28-AUG-2015",
  "report_date": "28-AUG-2015",
  "citations": [
    {
      "code": "2.50(c)(2)(2)",
      "kind": "",
      "repeat": false,
      "desc": "TIME AND METHOD OF IDENTIFICATION.",
      "narrative": "The licensee does not have a record book containing each animal's tag number, or microchip number, a written\ndescription of each animal, the data required by Sec. 2.75(a), and a clear photograph of each animal.\nThe required identification for dogs, including a clear photograph of each animal, is necessary to ensure all dogs\ncan be properly identified for oversight of their care and use in transport and in exhibition.\nThe licensee shall make a record book that contains all of the required identification information including a clear\nphotograph of each animal.\nTo be corrected by 9/12/2015.\nInspection conducted with licensee and AC inspectors, Cindy Rhodes and Tracy Thompson, DVM, at the Colorado\nState Fair, Pueblo, CO.\nExit interview conducted with facility representative.\nAdditional Inspectors\nRhodes Cindy, Animal Care Inspector"
    }
  ],
  "narrative": "2.50(c)(2)(2)\nTIME AND METHOD OF IDENTIFICATION.\nThe licensee does not have a record book containing each animal's tag number, or microchip number, a written\ndescription of each animal, the data required by Sec. 2.75(a), and a clear photograph of each animal.  \nThe required identification for dogs, including a clear photograph of each animal, is necessary to ensure all dogs\ncan be properly identified for oversight of their care and use in transport and in exhibition.\nThe licensee shall make a record book that contains all of the required identification information including a clear\nphotograph of each animal.\nTo be corrected by 9/12/2015.\nInspection conducted with licensee and AC inspectors, Cindy Rhodes and Tracy Thompson, DVM, at the Colorado\nState Fair, Pueblo, CO.\nExit interview conducted with facility representative.\nAdditional Inspectors\nRhodes Cindy, Animal Care Inspector",
  "animals_total": 11,
  "species": [
    {
      "count": 11,
      "scientific": "Canis lupus familiaris",
      "common": "DOG ADULT"
    }
  ]
}