{
  "insp_id": "223141157080808",
  "layout": "a",
  "customer_id": "1666",
  "customer_name": "Wyoming Game & Fish Department",
  "customer_addr": "2362 Highway 34\nWheatland, WY 82201",
  "certificate": "83-R-0005",
  "site_id": "001",
  "site_name": "WYOMING FISH & GAME",
  "insp_type": "ROUTINE INSPECTION",
  "date": "05-AUG-2014",
  "report_date": "11-AUG-2014",
  "citations": [],
  "narrative": "No non-compliant items identified during this inspection. \n \nExit interview conducted with facility representatives.",
  "animals_total": 92,
  "species": [
    {
      "count": 2,
      "scientific": "Alces alces",
      "common": "MOOSE"
    },
    {
      "count": 4,
      "scientific": "Bison bison",
      "common": "AMERICAN BISON"
    },
    {
      "count": 86,
      "scientific": "Cervus c. canadensis",
      "common": "ELK"
    }
  ]
}