{
  "insp_id": "2016082569728713",
  "layout": "a",
  "customer_id": "123",
  "customer_name": "Celldex Therapeutics",
  "customer_addr": "119 Fourth Avenue\nNeedham, MA 02494",
  "certificate": "14-R-0027",
  "site_id": "001",
  "site_name": "CELLDEX THERAPEUTICS",
  "insp_type": "ROUTINE INSPECTION",
  "date": "20-FEB-2020",
  "report_date": "20-FEB-2020",
  "animals_total": 13,
  "species": [
    {
      "count": 13,
      "scientific": "Oryctolagus cuniculus",
      "common": "DOMESTIC RABBIT / EUROPEAN RABBIT"
    }
  ]
}