{
  "insp_id": "INS-0000812598",
  "layout": "b",
  "customer_id": "504708",
  "customer_name": "Landon Headings",
  "customer_addr": "3481 State Hwy 73\nBUFFALO, MO 65622",
  "certificate": "43-A-6343",
  "site_id": "001",
  "site_name": "LANDON HEADINGS",
  "insp_type": "ROUTINE INSPECTION",
  "date": "01-SEP-2022",
  "animals_total": 252,
  "species": [
    {
      "count": 157,
      "scientific": "Canis lupus familiaris",
      "common": "DOG ADULT"
    },
    {
      "count": 95,
      "scientific": "Canis lupus familiaris",
      "common": "DOG PUPPY"
    }
  ]
}