{
  "insp_id": "INS-0000823141",
  "layout": "b",
  "customer_id": "8066",
  "customer_name": "BEN GRABER",
  "customer_addr": "9643 E 875 N\nODON, IN 47562",
  "certificate": "32-A-0190",
  "site_id": "001",
  "site_name": "BEN GRABER",
  "insp_type": "ROUTINE INSPECTION",
  "date": "18-OCT-2022",
  "animals_total": 62,
  "species": [
    {
      "count": 45,
      "scientific": "Canis lupus familiaris",
      "common": "DOG ADULT"
    },
    {
      "count": 17,
      "scientific": "Canis lupus familiaris",
      "common": "DOG PUPPY"
    }
  ]
}