{
  "insp_id": "INS-0000923600",
  "layout": "c",
  "customer_id": "335594",
  "customer_name": "Joinn Laboratories",
  "customer_addr": "2600 Hilltop Drive, Building C\nRichmond, CA 94806",
  "certificate": "93-R-0594",
  "site_id": "001",
  "site_name": "Joinn Laboratories CA Inc.",
  "insp_type": "ROUTINE INSPECTION",
  "date": "30-JAN-2024",
  "report_date": "01-FEB-2024",
  "citations": [],
  "narrative": "No non-compliant items were identified during this inspection. \n \nThis inspection and exit interview were conducted with facility representatives. \n \nAdditional Inspectors: \nKATHARINE FRANK, VETERINARY MEDICAL OFFICER \nGWENDALYN MAGINNIS, Nonhuman Primate Field Specialist n",
  "animals_total": 199,
  "species": [
    {
      "count": 199,
      "scientific": "Macaca fascicularis",
      "common": "CRAB-EATING MACAQUE / CYNOMOLGUS MONKEY"
    }
  ]
}