{
  "insp_id": "INS-0001351893",
  "layout": "c",
  "customer_id": "6023789",
  "customer_name": "SanusBio Research, LLC",
  "customer_addr": "24 Arnoldsville Rd\nCrawford, GA 30630",
  "certificate": "67-R-0007",
  "site_id": "001",
  "site_name": "SanusBio Research LLC",
  "insp_type": "ROUTINE INSPECTION",
  "date": "24-JUN-2025",
  "report_date": "30-JUN-2025",
  "citations": [],
  "narrative": "No regulated activity.  \n \nNo non-compliant items identified during this inspection. \n \nThis inspection and exit interview were conducted with a facility representative. \n \n n",
  "animals_total": 0,
  "species": [
    {
      "count": 0,
      "scientific": "NONE",
      "common": "NONE"
    }
  ]
}