{
  "insp_id": "282140715396218",
  "layout": "a",
  "customer_id": "930",
  "customer_name": "University Of South Florida",
  "customer_addr": "12901 Bruce B Downs Blvd Mdc 20\nTampa, FL 33612",
  "certificate": "58-R-0015",
  "site_id": "001",
  "site_name": "UNIVERSITY OF SOUTH FLORIDA",
  "insp_type": "ROUTINE INSPECTION",
  "date": "16-DEC-2014",
  "animals_total": 27,
  "species": [
    {
      "count": 2,
      "scientific": "Felis silvestris catus",
      "common": "CAT ADULT"
    },
    {
      "count": 4,
      "scientific": "Gerbillus acticola",
      "common": "BERBERA GERBIL"
    },
    {
      "count": 21,
      "scientific": "Mesocricetus auratus",
      "common": "SYRIAN / GOLDEN HAMSTER (COMMON PET/RESEARCH TYPE)"
    }
  ]
}