{
  "insp_id": "2016082568272079",
  "layout": "a",
  "customer_id": "501338",
  "customer_name": "Eli Hostetler",
  "customer_addr": "8899 C R 245\nHolmesville, OH 44633",
  "certificate": "31-A-0653",
  "site_id": "001",
  "site_name": "ELI HOSTETLER",
  "insp_type": "PRELICENSE INSPECTION #1",
  "date": "04-MAY-2017",
  "report_date": "04-MAY-2017",
  "animals_total": 14,
  "species": [
    {
      "count": 13,
      "scientific": "Canis lupus familiaris",
      "common": "DOG ADULT"
    },
    {
      "count": 1,
      "scientific": "Canis lupus familiaris",
      "common": "DOG PUPPY"
    }
  ]
}