{
  "insp_id": "INS-0000877804",
  "layout": "c",
  "customer_id": "6015510",
  "customer_name": "Dylan Burnett",
  "customer_addr": "329 Caxton Farms Court\nInman, SC 29349",
  "certificate": "56-C-0283",
  "site_id": "001",
  "site_name": "Burnett Exotics",
  "insp_type": "ROUTINE INSPECTION",
  "date": "27-JUN-2023",
  "report_date": "30-JUN-2023",
  "citations": [],
  "narrative": "No non-compliant items identified during this inspection. \n \nThis inspection and exit interview were conducted with the Licensee. \n \n n",
  "animals_total": 19,
  "species": [
    {
      "count": 3,
      "scientific": "Sus scrofa domestica",
      "common": "DOMESTIC PIG / POTBELLY PIG / MICRO PIG"
    },
    {
      "count": 1,
      "scientific": "Hystrix cristata",
      "common": "AFRICAN CRESTED PORCUPINE"
    },
    {
      "count": 1,
      "scientific": "Dolichotis patagonum",
      "common": "PATAGONIAN CAVY / MARA"
    },
    {
      "count": 5,
      "scientific": "Atelerix albiventris",
      "common": "FOUR-TOED HEDGEHOG"
    },
    {
      "count": 5,
      "scientific": "Oryctolagus cuniculus",
      "common": "DOMESTIC RABBIT / EUROPEAN RABBIT"
    },
    {
      "count": 4,
      "scientific": "Petaurus breviceps",
      "common": "SUGAR GLIDER"
    }
  ]
}