{
  "insp_id": "2016090000755307",
  "layout": "b",
  "customer_id": "39311",
  "customer_name": "Carroll Bailey",
  "customer_addr": "2020 STATE HWY 59\nGOODMAN, MO 64843",
  "certificate": "43-B-3609",
  "site_id": "001",
  "site_name": "CARROLL BAILEY",
  "insp_type": "RE-LICENSE INSPECTION",
  "date": "02-DEC-2021",
  "report_date": "10-DEC-2021",
  "citations": [],
  "narrative": "No non-compliant items were identified during this Re-License inspection. \n \nThis is a 1st Re-License Inspection for a Class A license. The inspection and exit briefing were conducted with the \napplicant. The applicant is ready to be licensed under the AWA. \n \nA copy of your license will be sent to you without any additional action on your part. If you have not received your license \nwithin 30 days, please contact the USDA at 970-494-7478. \n \nEnd Section",
  "animals_total": 50,
  "species": [
    {
      "count": 26,
      "scientific": "Canis lupus familiaris",
      "common": "DOG ADULT"
    },
    {
      "count": 24,
      "scientific": "Canis lupus familiaris",
      "common": "DOG PUPPY"
    }
  ]
}