{
  "insp_id": "2016082568989929",
  "layout": "a",
  "customer_id": "333858",
  "customer_name": "David Davenport",
  "customer_addr": "Sandra Davenport\n585 Dutton Mountain Road\nCenter Ridge, AR 72027",
  "certificate": "71-A-1348",
  "site_id": "001",
  "site_name": "DAVID DAVENPORT, SANDRA DAVENPORT",
  "insp_type": "ROUTINE INSPECTION",
  "date": "06-DEC-2017",
  "report_date": "06-DEC-2017",
  "citations": [],
  "narrative": "No non-compliant items identified during this inspection.\nThis inspection and exit briefing were conducted with the owners and Karl Thornton, ACI.",
  "animals_total": 176,
  "species": [
    {
      "count": 121,
      "scientific": "Canis lupus familiaris",
      "common": "DOG ADULT"
    },
    {
      "count": 55,
      "scientific": "Canis lupus familiaris",
      "common": "DOG PUPPY"
    }
  ]
}