{
  "insp_id": "2016090000721887",
  "layout": "a",
  "customer_id": "331477",
  "customer_name": "TERRY GUOAN",
  "customer_addr": "4619 M-61\nSTANDISH, MI 48658",
  "certificate": "34-C-0433",
  "site_id": "001",
  "site_name": "TERRY GUOAN",
  "insp_type": "ROUTINE INSPECTION",
  "date": "23-SEP-2021",
  "animals_total": 3,
  "species": [
    {
      "count": 1,
      "scientific": "Chlorocebus aethiops",
      "common": "AFRICAN GREEN MONKEY / GRIVET"
    },
    {
      "count": 1,
      "scientific": "Camelus bactrianus",
      "common": "BACTRIAN CAMEL"
    },
    {
      "count": 1,
      "scientific": "Hystrix cristata",
      "common": "AFRICAN CRESTED PORCUPINE"
    }
  ]
}