{
  "insp_id": "INS-0000812652",
  "layout": "c",
  "customer_id": "332361",
  "customer_name": "David Brown",
  "customer_addr": "14059 South 4440 Road\nBLUEJACKET, OK 74333",
  "certificate": "73-A-2712",
  "site_id": "001",
  "site_name": "Dave Brown",
  "insp_type": "ROUTINE INSPECTION",
  "date": "31-AUG-2022",
  "report_date": "02-SEP-2022",
  "citations": [],
  "narrative": "No non-compliant items identified during this inspection. \n \nThis inspection and exit interview were conducted with facility representative. \n \n n",
  "animals_total": 107,
  "species": [
    {
      "count": 85,
      "scientific": "Canis lupus familiaris",
      "common": "DOG ADULT"
    },
    {
      "count": 22,
      "scientific": "Canis lupus familiaris",
      "common": "DOG PUPPY"
    }
  ]
}