{
  "insp_id": "2016082569500631",
  "layout": "a",
  "customer_id": "505195",
  "customer_name": "Linda Gray",
  "customer_addr": "17300 State Rt B\nSaint James, MO 65559",
  "certificate": "43-A-6375",
  "site_id": "001",
  "site_name": "LINDA GRAY",
  "insp_type": "ROUTINE INSPECTION",
  "date": "30-MAY-2019",
  "animals_total": 13,
  "species": [
    {
      "count": 9,
      "scientific": "Canis lupus familiaris",
      "common": "DOG ADULT"
    },
    {
      "count": 4,
      "scientific": "Canis lupus familiaris",
      "common": "DOG PUPPY"
    }
  ]
}