{
  "insp_id": "2016082568228226",
  "layout": "a",
  "customer_id": "30591",
  "customer_name": "Doedi Beth Britt",
  "customer_addr": "30712 State Highway 3\nCallao, MO 63534",
  "certificate": "43-A-5762",
  "site_id": "001",
  "site_name": "DOEDI BETH BRITT",
  "insp_type": "ROUTINE INSPECTION",
  "date": "27-APR-2017",
  "animals_total": 10,
  "species": [
    {
      "count": 6,
      "scientific": "Canis lupus familiaris",
      "common": "DOG ADULT"
    },
    {
      "count": 4,
      "scientific": "Canis lupus familiaris",
      "common": "DOG PUPPY"
    }
  ]
}