{
  "insp_id": "28151641120138",
  "layout": "a",
  "customer_id": "322039",
  "customer_name": "Teske Pet And Garden Center",
  "customer_addr": "2423 16th Street\nMoline, IL 61265",
  "certificate": "33-B-0427",
  "site_id": "003",
  "site_name": "BETTENDORF TESKES",
  "insp_type": "ROUTINE INSPECTION",
  "date": "28-JAN-2015",
  "animals_total": 16,
  "species": [
    {
      "count": 1,
      "scientific": "Canis lupus familiaris",
      "common": "DOG PUPPY"
    },
    {
      "count": 3,
      "scientific": "Cavia porcellus",
      "common": "DOMESTIC GUINEA PIG"
    },
    {
      "count": 2,
      "scientific": "Cricetus cricetus",
      "common": "EUROPEAN HAMSTER / BLACK-BELLIED HAMSTER"
    },
    {
      "count": 2,
      "scientific": "Felis silvestris catus",
      "common": "CAT KITTEN"
    },
    {
      "count": 8,
      "scientific": "Oryctolagus cuniculus",
      "common": "EUROPEAN RABBIT"
    }
  ]
}