{
  "insp_id": "2016082569517749",
  "layout": "a",
  "customer_id": "328105",
  "customer_name": "Marilyn Miller",
  "customer_addr": "1565 C R 1800 N\nSullivan, IL 61951",
  "certificate": "33-A-0533",
  "site_id": "001",
  "site_name": "MARILYN MILLER",
  "insp_type": "ROUTINE INSPECTION",
  "date": "19-JUN-2019",
  "report_date": "19-JUN-2019",
  "citations": [],
  "narrative": "No non-compliant items identified during this inspection.\nThis inspection and exit interview were conducted with the kennel manager.",
  "animals_total": 22,
  "species": [
    {
      "count": 10,
      "scientific": "Canis lupus familiaris",
      "common": "DOG ADULT"
    },
    {
      "count": 12,
      "scientific": "Canis lupus familiaris",
      "common": "DOG PUPPY"
    }
  ]
}