{
  "insp_id": "2016082569589740",
  "layout": "a",
  "customer_id": "3386",
  "customer_name": "Musk Ox Development Corporation",
  "customer_addr": "P O Box 587\nPalmer, AK 99645",
  "certificate": "96-C-0031",
  "site_id": "001",
  "site_name": "MUSK OX DEVELOPMENT CORP.",
  "insp_type": "ROUTINE INSPECTION",
  "date": "23-AUG-2019",
  "report_date": "30-AUG-2019",
  "animals_total": 82,
  "species": [
    {
      "count": 82,
      "scientific": "Ovibos moschatus",
      "common": "MUSKOX"
    }
  ]
}