{
  "insp_id": "39161216000808",
  "layout": "a",
  "customer_id": "44121",
  "customer_name": "Best Exotics L L C",
  "customer_addr": "1777 County Road 3211\nNaples, TX 75568",
  "certificate": "74-B-0756",
  "site_id": "001",
  "site_name": "Best Exotics L L C",
  "insp_type": "PRELICENSE INSPECTION #1",
  "date": "08-FEB-2016",
  "report_date": "08-FEB-2016",
  "citations": [],
  "narrative": "This inspection and exit interview conducted by Donnovan L. Fox ACI with the Applicants.\nNo noncompliance identified this inspection.\n\"OK\" to license as a class \"B\" Dealer.\nApplicant must send to the Western Regional Office of Animal Care the amount of $60.00 for license fee. The\naddress to send license fee to is:\nAPHIS, USDA, ANIMAL CARE\n2150 CENTRE AVENUE BLDG. \"B\" MAIL STOP 3W11\nFT. COLLINS, CO 80526-8117\n\"NO\" activities requiring a USDA license may be conducted until receipt of license. \nEND OF REPORT.",
  "animals_total": 11,
  "species": [
    {
      "count": 2,
      "scientific": "Cynomys gunnisoni",
      "common": "GUNNISON'S PRAIRIE DOG"
    },
    {
      "count": 4,
      "scientific": "Lemur catta",
      "common": "RINGTAIL LEMUR"
    },
    {
      "count": 2,
      "scientific": "Petaurus breviceps",
      "common": "SUGAR GLIDER"
    },
    {
      "count": 3,
      "scientific": "Sciurus carolinensis",
      "common": "EASTERN GREY SQUIRREL"
    }
  ]
}