{
  "insp_id": "2016090000711083",
  "layout": "b",
  "customer_id": "3141",
  "customer_name": "Louisville Zoological Garden",
  "customer_addr": "PO Box 37250\nLOUISVILLE, KY 40233",
  "certificate": "61-C-0106",
  "site_id": "001",
  "site_name": "LOUISVILLE ZOOLOGICAL GARDEN",
  "insp_type": "ROUTINE INSPECTION",
  "date": "13-SEP-2021",
  "report_date": "14-SEP-2021",
  "citations": [],
  "narrative": "No non-compliant items identified during this inspection. \n \nThis inspection was conducted with the Senior Staff Veterinarian and other facility representatives. \n \nThe exit interview was conducted with the Senior Staff Veterinarian, Director, Assistant Director, and General Curator. \n \nAdditional Inspectors: \nRania Gollakner, VETERINARY MEDICAL OFFICEREnd Section",
  "animals_total": 215,
  "species": [
    {
      "count": 2,
      "scientific": "Lagothrix lagotricha",
      "common": "WOOLLY MONKEY"
    },
    {
      "count": 9,
      "scientific": "Gorilla gorilla",
      "common": "WESTERN GORILLA"
    },
    {
      "count": 2,
      "scientific": "Pongo pygmaeus",
      "common": "BORNEAN ORANGUTAN"
    },
    {
      "count": 2,
      "scientific": "Symphalangus syndactylus",
      "common": "SIAMANG"
    },
    {
      "count": 3,
      "scientific": "Zalophus californianus",
      "common": "CALIFORNIA SEA LION"
    },
    {
      "count": 2,
      "scientific": "Phoca vitulina",
      "common": "HARBOR SEAL"
    },
    {
      "count": 2,
      "scientific": "Ursus maritimus",
      "common": "POLAR BEAR"
    },
    {
      "count": 1,
      "scientific": "Lama guanicoe",
      "common": "GUANACO"
    },
    {
      "count": 11,
      "scientific": "Capra hircus",
      "common": "DOMESTIC GOAT"
    },
    {
      "count": 2,
      "scientific": "Chrysocyon brachyurus",
      "common": "MANED WOLF"
    },
    {
      "count": 1,
      "scientific": "Panthera onca",
      "common": "JAGUAR"
    },
    {
      "count": 3,
      "scientific": "Uncia uncia",
      "common": "SNOW LEOPARD"
    },
    {
      "count": 3,
      "scientific": "Panthera leo",
      "common": "LION"
    },
    {
      "count": 1,
      "scientific": "Puma concolor",
      "common": "PUMA / MOUNTAIN LION / COUGAR"
    },
    {
      "count": 4,
      "scientific": "Panthera tigris",
      "common": "TIGER"
    },
    {
      "count": 11,
      "scientific": "Heterocephalus glaber",
      "common": "NAKED MOLE-RAT"
    },
    {
      "count": 1,
      "scientific": "Coendou prehensilis",
      "common": "PREHENSILE-TAILED PORCUPINE"
    },
    {
      "count": 5,
      "scientific": "Addax nasomaculatus",
      "common": "ADDAX"
    },
    {
      "count": 4,
      "scientific": "Tragelaphus eurycerus",
      "common": "BONGO"
    },
    {
      "count": 2,
      "scientific": "Camelus dromedarius",
      "common": "DROMEDARY CAMEL"
    },
    {
      "count": 3,
      "scientific": "Equus zebra",
      "common": "MOUNTAIN ZEBRA / HARTMANN'S ZEBRA"
    },
    {
      "count": 2,
      "scientific": "Babyrousa babyrussa",
      "common": "BABIRUSA"
    },
    {
      "count": 2,
      "scientific": "Phacochoerus africanus",
      "common": "WARTHOG"
    },
    {
      "count": 2,
      "scientific": "Tolypeutes matacus",
      "common": "SOUTHERN THREE-BANDED ARMADILLO"
    },
    {
      "count": 45,
      "scientific": "Desmodus rotundus",
      "common": "COMMON VAMPIRE BAT"
    },
    {
      "count": 8,
      "scientific": "Pteropus rodricensis",
      "common": "RODRIGUES FLYING FOX"
    },
    {
      "count": 1,
      "scientific": "Elephas maximus",
      "common": "ASIAN ELEPHANT"
    },
    {
      "count": 2,
      "scientific": "Loxodonta africana",
      "common": "AFRICAN ELEPHANT"
    },
    {
      "count": 21,
      "scientific": "Mustela nigripes",
      "common": "BLACK-FOOTED FERRET"
    },
    {
      "count": 2,
      "scientific": "Giraffa camelopardalis",
      "common": "GIRAFFE"
    },
    {
      "count": 1,
      "scientific": "Hexaprotodon liberiensis",
      "common": "PYGMY HIPPOPOTAMUS"
    },
    {
      "count": 1,
      "scientific": "Procavia capensis",
      "common": "ROCK HYRAX"
    },
    {
      "count": 5,
      "scientific": "Suricata suricatta",
      "common": "SLENDER-TAILED MEERKAT"
    },
    {
      "count": 2,
      "scientific": "Didelphis virginiana",
      "common": "VIRGINIA OPOSSUM"
    },
    {
      "count": 2,
      "scientific": "Mustela putorius",
      "common": "EUROPEAN POLECAT"
    },
    {
      "count": 2,
      "scientific": "Ceratotherium simum",
      "common": "WHITE RHINOCEROS"
    },
    {
      "count": 2,
      "scientific": "Tapirus indicus",
      "common": "MALAYAN TAPIR"
    },
    {
      "count": 8,
      "scientific": "Notamacropus rufogriseus",
      "common": "BENNETT'S WALLABY / RED-NECKED WALLABY"
    },
    {
      "count": 4,
      "scientific": "Osphranter robustus",
      "common": "HILL WALLAROO"
    },
    {
      "count": 3,
      "scientific": "Atelerix albiventris",
      "common": "FOUR-TOED HEDGEHOG (MOST COMMON PET HEDGEHOG)"
    },
    {
      "count": 1,
      "scientific": "Oryctolagus cuniculus",
      "common": "DOMESTIC RABBIT / EUROPEAN RABBIT"
    },
    {
      "count": 4,
      "scientific": "Lemur catta",
      "common": "RING-TAILED LEMUR"
    },
    {
      "count": 2,
      "scientific": "Chinchilla lanigera",
      "common": "CHINCHILLA (DOMESTICATED)"
    },
    {
      "count": 3,
      "scientific": "Ursus arctos",
      "common": "BROWN BEAR"
    },
    {
      "count": 2,
      "scientific": "Choloepus didactylus",
      "common": "LINNAEUS'S TWO-TOED SLOTH"
    },
    {
      "count": 2,
      "scientific": "Pongo abelii",
      "common": "SUMATRAN ORANGUTAN"
    },
    {
      "count": 4,
      "scientific": "Halichoerus grypus",
      "common": "GREY SEAL"
    },
    {
      "count": 3,
      "scientific": "Colobus guereza",
      "common": "EASTERN BLACK-AND-WHITE COLOBUS / GUEREZA"
    },
    {
      "count": 2,
      "scientific": "Lynx canadensis",
      "common": "CANADIAN LYNX"
    },
    {
      "count": 3,
      "scientific": "Cercopithecus ascanius",
      "common": "RED-TAILED MONKEY"
    }
  ]
}