{
  "insp_id": "55141410032212",
  "layout": "a",
  "customer_id": "329797",
  "customer_name": "Jacob K Lapp",
  "customer_addr": "12547 Madden Road\nBelmont, WI 53510",
  "certificate": "35-A-0353",
  "site_id": "001",
  "site_name": "JACOB K LAPP",
  "insp_type": "ROUTINE INSPECTION",
  "date": "26-FEB-2014",
  "report_date": "26-FEB-2014",
  "animals_total": 1243,
  "species": [
    {
      "count": 1243,
      "scientific": "Cavia porcellus",
      "common": "DOMESTIC GUINEA PIG"
    }
  ]
}