{
  "insp_id": "2016090000720864",
  "layout": "b",
  "customer_id": "13792",
  "customer_name": "Linda Crane",
  "customer_addr": "5449 Hwy 17\nEunice, MO 65468",
  "certificate": "43-A-3362",
  "site_id": "001",
  "site_name": "LINDA L. CRANE",
  "insp_type": "ROUTINE INSPECTION",
  "date": "22-SEP-2021",
  "report_date": "23-SEP-2021",
  "citations": [],
  "narrative": "No non-compliant items identified during this inspection. \n \nThis inspection and exit interview were conducted with licensee. \n \nEnd Section",
  "animals_total": 75,
  "species": [
    {
      "count": 44,
      "scientific": "Canis lupus familiaris",
      "common": "DOG ADULT"
    },
    {
      "count": 31,
      "scientific": "Canis lupus familiaris",
      "common": "DOG PUPPY"
    }
  ]
}