{
  "insp_id": "278152010210421",
  "layout": "a",
  "customer_id": "3213",
  "customer_name": "Duke Lemur Center",
  "customer_addr": "3705 Erwin Rd.\nDurham, NC 27705",
  "certificate": "55-C-0110",
  "site_id": "001",
  "site_name": "DUKE LEMUR CENTER",
  "insp_type": "ROUTINE INSPECTION",
  "date": "18-SEP-2015",
  "report_date": "18-SEP-2015",
  "animals_total": 242,
  "species": [
    {
      "count": 22,
      "scientific": "Cheirogaleus medius",
      "common": "FAT-TAILED DWARF LEMUR"
    },
    {
      "count": 14,
      "scientific": "Daubentonia madagascariensis",
      "common": "AYE-AYE"
    },
    {
      "count": 12,
      "scientific": "Eulemur coronatus",
      "common": "CROWNED LEMUR"
    },
    {
      "count": 12,
      "scientific": "Eulemur fulvus",
      "common": "COMMON BROWN LEMUR"
    },
    {
      "count": 15,
      "scientific": "Eulemur macaco",
      "common": "BLACK LEMUR"
    },
    {
      "count": 10,
      "scientific": "Eulemur mongoz",
      "common": "MONGOOSE LEMUR"
    },
    {
      "count": 3,
      "scientific": "Eulemur rubriventer",
      "common": "RED-BELLIED LEMUR"
    },
    {
      "count": 3,
      "scientific": "Hapalemur griseus",
      "common": "GREY GENTLE LEMUR"
    },
    {
      "count": 33,
      "scientific": "Lemur catta",
      "common": "RING-TAILED LEMUR"
    },
    {
      "count": 1,
      "scientific": "Loris tardigradus",
      "common": "SLENDER LORIS"
    },
    {
      "count": 53,
      "scientific": "Microcebus murinus",
      "common": "LESSER MOUSE LEMUR"
    },
    {
      "count": 1,
      "scientific": "Nycticebus coucang",
      "common": "SLOW LORIS"
    },
    {
      "count": 5,
      "scientific": "Nycticebus pygmaeus",
      "common": "PYGMY SLOW LORIS"
    },
    {
      "count": 1,
      "scientific": "Otolemur crassicaudatus",
      "common": "GREATER BUSHBABY"
    },
    {
      "count": 32,
      "scientific": "Propithecus coquereli",
      "common": "COQUEREL'S SIFAKA"
    },
    {
      "count": 17,
      "scientific": "Varecia rubra",
      "common": "RED RUFFED LEMUR"
    },
    {
      "count": 8,
      "scientific": "Varecia variegata",
      "common": "BLACK-AND-WHITE RUFFED LEMUR"
    }
  ]
}