{
  "insp_id": "2016082569404903",
  "layout": "a",
  "customer_id": "3532",
  "customer_name": "Los Angeles Zoo",
  "customer_addr": "5333 Zoo Drive\nLos Angeles, CA 90027",
  "certificate": "93-C-0043",
  "site_id": "001",
  "site_name": "LOS ANGELES ZOO",
  "insp_type": "FOCUSED INSPECTION",
  "date": "14-MAR-2019",
  "report_date": "18-MAR-2019",
  "citations": [],
  "narrative": "No non-compliant items identified during this inspection.\nThis inspection and exit interview were conducted with the facility representative.\nAdditional Inspectors\nFields Tyler, Veterinary Medical Officer",
  "animals_total": 37,
  "species": [
    {
      "count": 4,
      "scientific": "Elephas maximus",
      "common": "ASIAN ELEPHANT"
    },
    {
      "count": 5,
      "scientific": "Giraffa camelopardalis",
      "common": "GIRAFFE"
    },
    {
      "count": 6,
      "scientific": "Gorilla gorilla",
      "common": "WESTERN GORILLA"
    },
    {
      "count": 15,
      "scientific": "Pan troglodytes",
      "common": "CHIMPANZEE"
    },
    {
      "count": 7,
      "scientific": "Pongo pygmaeus",
      "common": "BORNEAN ORANGUTAN"
    }
  ]
}