{
  "insp_id": "2016082568870002",
  "layout": "a",
  "customer_id": "321938",
  "customer_name": "Peaceable Primate Sanctuary",
  "customer_addr": "6415 N 800 W\nWinamac, IN 46996",
  "certificate": "32-C-0261",
  "site_id": "001",
  "site_name": "PEACEABLE PRIMATE SANCTUARY",
  "insp_type": "ROUTINE INSPECTION",
  "date": "28-SEP-2017",
  "animals_total": 16,
  "species": [
    {
      "count": 12,
      "scientific": "Papio anubis",
      "common": "OLIVE BABOON"
    },
    {
      "count": 2,
      "scientific": "Papio hamadryas",
      "common": "HAMADRYAS BABOON"
    },
    {
      "count": 2,
      "scientific": "Papio papio",
      "common": "GUINEA BABOON"
    }
  ]
}