{
  "insp_id": "67161455330355",
  "layout": "a",
  "customer_id": "43005",
  "customer_name": "Natural History Education Co Of Midsouth",
  "customer_addr": "2464 Sowell Mill Pike\nColumbia, TN 38401",
  "certificate": "63-C-0207",
  "site_id": "001",
  "site_name": "NATURAL HISTORY EDUCATION CO OF MIDSOUTH",
  "insp_type": "ROUTINE INSPECTION",
  "date": "07-MAR-2016",
  "animals_total": 12,
  "species": [
    {
      "count": 3,
      "scientific": "Atelerix albiventris",
      "common": "HEDGEHOG"
    },
    {
      "count": 1,
      "scientific": "Capra hircus",
      "common": "DOMESTIC GOAT"
    },
    {
      "count": 2,
      "scientific": "Cynomys ludovicianus",
      "common": "BLACK-TAILED PRAIRIE DOG"
    },
    {
      "count": 2,
      "scientific": "Eidolon helvum",
      "common": "STRAW-COLOURED FRUIT BAT"
    },
    {
      "count": 2,
      "scientific": "Glaucomys volans",
      "common": "SOUTHERN FLYING SQUIRREL"
    },
    {
      "count": 1,
      "scientific": "Muntiacus reevesi",
      "common": "REEVE'S MUNTJAC"
    },
    {
      "count": 1,
      "scientific": "Nasua nasua",
      "common": "SOUTH AMERICAN COATI"
    }
  ]
}