{
  "insp_id": "2016082569741998",
  "layout": "a",
  "customer_id": "44986",
  "customer_name": "Rita Mondus",
  "customer_addr": "1276 E Green Bay Street\nShawano, WI 54166",
  "certificate": "35-C-0361",
  "site_id": "002",
  "site_name": "WINTER HOME",
  "insp_type": "ROUTINE INSPECTION",
  "date": "26-FEB-2020",
  "report_date": "26-FEB-2020",
  "animals_total": 10,
  "species": [
    {
      "count": 1,
      "scientific": "Dolichotis patagonum",
      "common": "PATAGONIAN CAVY / MARA"
    },
    {
      "count": 1,
      "scientific": "Hydrochaeris hydrochaeris",
      "common": "CAPYBARA"
    },
    {
      "count": 2,
      "scientific": "Nasua narica",
      "common": "WHITE-NOSED COATI"
    },
    {
      "count": 1,
      "scientific": "Nasuella olivacea",
      "common": "MOUNTAIN COATI"
    },
    {
      "count": 1,
      "scientific": "Notamacropus rufogriseus",
      "common": "BENNETT'S WALLABY / RED-NECKED WALLABY"
    },
    {
      "count": 1,
      "scientific": "Oryctolagus cuniculus",
      "common": "DOMESTIC RABBIT / EUROPEAN RABBIT"
    },
    {
      "count": 1,
      "scientific": "Osphranter rufus",
      "common": "RED KANGAROO"
    },
    {
      "count": 2,
      "scientific": "Vulpes zerda",
      "common": "FENNEC FOX"
    }
  ]
}