{
  "insp_id": "13151018200390",
  "layout": "a",
  "customer_id": "5901",
  "customer_name": "Larry Engel",
  "customer_addr": "56457 280th Ave\nPalmer, IA 50571",
  "certificate": "42-A-1385",
  "site_id": "001",
  "site_name": "LARRY ENGEL",
  "insp_type": "ROUTINE INSPECTION",
  "date": "12-JAN-2015",
  "report_date": "13-JAN-2015",
  "citations": [],
  "narrative": "No non-compliant items identified during this inspection. \n \nExit interview conducted with facility representative.",
  "animals_total": 30,
  "species": [
    {
      "count": 12,
      "scientific": "Canis lupus familiaris",
      "common": "DOG ADULT"
    },
    {
      "count": 18,
      "scientific": "Canis lupus familiaris",
      "common": "DOG PUPPY"
    }
  ]
}