{
  "insp_id": "2016090000776427",
  "layout": "a",
  "customer_id": "9059",
  "customer_name": "Elm Hill Labs Inc",
  "customer_addr": "7 Kidder Rd.\nChelmsford, MA 01824",
  "certificate": "14-A-0017",
  "site_id": "002",
  "site_name": "Elm Hill Labs Inc",
  "insp_type": "RE-LICENSE INSPECTION",
  "date": "23-MAR-2022",
  "report_date": "23-MAR-2022",
  "animals_total": 2402,
  "species": [
    {
      "count": 2402,
      "scientific": "Cavia porcellus",
      "common": "DOMESTIC GUINEA PIG"
    }
  ]
}