{
  "insp_id": "2016082569121016",
  "layout": "a",
  "customer_id": "329613",
  "customer_name": "Cardinal Industries",
  "customer_addr": "47 Pierce Est\nHawkinsville, GA 31036",
  "certificate": "57-C-0354",
  "site_id": "001",
  "site_name": "CARDINAL INDUSTRIES",
  "insp_type": "ROUTINE INSPECTION",
  "date": "16-APR-2018",
  "animals_total": 1,
  "species": [
    {
      "count": 1,
      "scientific": "Equus quagga",
      "common": "BURCHELL\u2019S / GRANT\u2019S / CHAPMAN\u2019S / PLAINS ZEBRA"
    }
  ]
}