{
  "insp_id": "INS-0000814676",
  "layout": "c",
  "customer_id": "6011388",
  "customer_name": "Grandview Puppies LLC",
  "customer_addr": "2272 200th Ave\nPorter, MN 56280",
  "certificate": "41-A-0508",
  "site_id": "001",
  "site_name": "Grandview Puppies LLC",
  "insp_type": "ROUTINE INSPECTION",
  "date": "09-SEP-2022",
  "report_date": "09-SEP-2022",
  "citations": [],
  "narrative": "No non-compliant items identified during this inspection. \nThis inspection and exit interview were conducted with President. \nEnd of report. \n \n n",
  "animals_total": 80,
  "species": [
    {
      "count": 76,
      "scientific": "Canis lupus familiaris",
      "common": "DOG ADULT"
    },
    {
      "count": 4,
      "scientific": "Canis lupus familiaris",
      "common": "DOG PUPPY"
    }
  ]
}