{
  "insp_id": "39151032520197",
  "layout": "a",
  "customer_id": "332898",
  "customer_name": "Judy Slaughter",
  "customer_addr": "20728 Neosho Dr.\nLebanon, MO 65536",
  "certificate": "43-A-5933",
  "site_id": "001",
  "site_name": "JUDY SLAUGHTER",
  "insp_type": "PRELICENSE INSPECTION #1",
  "date": "26-JAN-2015",
  "report_date": "09-FEB-2015",
  "citations": [],
  "narrative": "This inspection began at 1100.\nNo non-compliant items identified during this inspection.\nExit interview conducted with facility representative.\nThis inspection was for a Class A License.\nNo regulated activity will take place until the license is issued.\nThe license fee will be mailed to the Western Regional Office with the report.\nEnd of report.",
  "animals_total": 63,
  "species": [
    {
      "count": 38,
      "scientific": "Canis lupus familiaris",
      "common": "DOG ADULT"
    },
    {
      "count": 25,
      "scientific": "Canis lupus familiaris",
      "common": "DOG PUPPY"
    }
  ]
}